ProgrammingLanguagesApplicationAndInterpretation/README.md
ProgrammingLanguagesApplicationAndInterpretation/__init__.py
ProgrammingLanguagesApplicationAndInterpretation/__main__.py
ProgrammingLanguagesApplicationAndInterpretation/file.epub
ProgrammingLanguagesApplicationAndInterpretation/index.html
ProgrammingLanguagesApplicationAndInterpretation/css/__init__.py
ProgrammingLanguagesApplicationAndInterpretation/css/annotations.css
ProgrammingLanguagesApplicationAndInterpretation/css/main.css
ProgrammingLanguagesApplicationAndInterpretation/css/normalize.css
ProgrammingLanguagesApplicationAndInterpretation/css/popup.css
ProgrammingLanguagesApplicationAndInterpretation/font/__init__.py
ProgrammingLanguagesApplicationAndInterpretation/font/fontello.eot
ProgrammingLanguagesApplicationAndInterpretation/font/fontello.svg
ProgrammingLanguagesApplicationAndInterpretation/font/fontello.ttf
ProgrammingLanguagesApplicationAndInterpretation/font/fontello.woff
ProgrammingLanguagesApplicationAndInterpretation/img/__init__.py
ProgrammingLanguagesApplicationAndInterpretation/img/annotator-glyph-sprite.png
ProgrammingLanguagesApplicationAndInterpretation/img/annotator-icon-sprite.png
ProgrammingLanguagesApplicationAndInterpretation/img/apple-touch-icon.png
ProgrammingLanguagesApplicationAndInterpretation/img/cancelfullscreen.png
ProgrammingLanguagesApplicationAndInterpretation/img/close.png
ProgrammingLanguagesApplicationAndInterpretation/img/fullscreen.png
ProgrammingLanguagesApplicationAndInterpretation/img/loader.gif
ProgrammingLanguagesApplicationAndInterpretation/img/menu-icon.png
ProgrammingLanguagesApplicationAndInterpretation/img/save.png
ProgrammingLanguagesApplicationAndInterpretation/img/saved.png
ProgrammingLanguagesApplicationAndInterpretation/img/settings-s.png
ProgrammingLanguagesApplicationAndInterpretation/img/settings.png
ProgrammingLanguagesApplicationAndInterpretation/img/star.png
ProgrammingLanguagesApplicationAndInterpretation/js/__init__.py
programming_languages_application_and_interpretation-2024.3.2.0.dist-info/METADATA
programming_languages_application_and_interpretation-2024.3.2.0.dist-info/WHEEL
programming_languages_application_and_interpretation-2024.3.2.0.dist-info/entry_points.txt
programming_languages_application_and_interpretation-2024.3.2.0.dist-info/top_level.txt
programming_languages_application_and_interpretation-2024.3.2.0.dist-info/RECORD
